slack_scim_rbac/__init__.py
slack_scim_rbac/middleware.py
slack_scim_rbac-0.1.0.dist-info/LICENSE
slack_scim_rbac-0.1.0.dist-info/WHEEL
slack_scim_rbac-0.1.0.dist-info/METADATA
slack_scim_rbac-0.1.0.dist-info/RECORD
