Metadata-Version: 2.1
Name: slack-scim-rbac
Version: 0.1.0
Summary: Role Based Access Control for Slack-Bolt applications
Home-page: https://github.com/jeremyschulman/slack-scim-rbac
License: Apache-2.0
Author: Jeremy Schulman
Requires-Python: >=3.8,<4.0
Classifier: License :: OSI Approved :: Apache Software License
Classifier: Programming Language :: Python :: 3
Classifier: Programming Language :: Python :: 3.8
Classifier: Programming Language :: Python :: 3.9
Requires-Dist: slack-bolt (>=1.6.0,<2.0.0)
Project-URL: Repository, https://github.com/jeremyschulman/slack-scim-rbac
